PracticalCryptographyForDevelopers/README.md
PracticalCryptographyForDevelopers/__init__.py
PracticalCryptographyForDevelopers/__main__.py
PracticalCryptographyForDevelopers/file.epub
PracticalCryptographyForDevelopers/index.html
PracticalCryptographyForDevelopers/css/__init__.py
PracticalCryptographyForDevelopers/css/annotations.css
PracticalCryptographyForDevelopers/css/main.css
PracticalCryptographyForDevelopers/css/normalize.css
PracticalCryptographyForDevelopers/css/popup.css
PracticalCryptographyForDevelopers/font/__init__.py
PracticalCryptographyForDevelopers/font/fontello.eot
PracticalCryptographyForDevelopers/font/fontello.svg
PracticalCryptographyForDevelopers/font/fontello.ttf
PracticalCryptographyForDevelopers/font/fontello.woff
PracticalCryptographyForDevelopers/img/__init__.py
PracticalCryptographyForDevelopers/img/annotator-glyph-sprite.png
PracticalCryptographyForDevelopers/img/annotator-icon-sprite.png
PracticalCryptographyForDevelopers/img/apple-touch-icon.png
PracticalCryptographyForDevelopers/img/cancelfullscreen.png
PracticalCryptographyForDevelopers/img/close.png
PracticalCryptographyForDevelopers/img/fullscreen.png
PracticalCryptographyForDevelopers/img/loader.gif
PracticalCryptographyForDevelopers/img/menu-icon.png
PracticalCryptographyForDevelopers/img/save.png
PracticalCryptographyForDevelopers/img/saved.png
PracticalCryptographyForDevelopers/img/settings-s.png
PracticalCryptographyForDevelopers/img/settings.png
PracticalCryptographyForDevelopers/img/star.png
PracticalCryptographyForDevelopers/js/__init__.py
PracticalCryptographyForDevelopers/js/epub.js
PracticalCryptographyForDevelopers/js/epub.min.js
PracticalCryptographyForDevelopers/js/epub.min.map
PracticalCryptographyForDevelopers/js/hooks.min.js
PracticalCryptographyForDevelopers/js/hooks.min.map
PracticalCryptographyForDevelopers/js/reader.js
PracticalCryptographyForDevelopers/js/reader.js.map
PracticalCryptographyForDevelopers/js/reader.min.js
practical_cryptography_for_developers-2024.3.4.0.dist-info/METADATA
practical_cryptography_for_developers-2024.3.4.0.dist-info/WHEEL
practical_cryptography_for_developers-2024.3.4.0.dist-info/entry_points.txt
practical_cryptography_for_developers-2024.3.4.0.dist-info/top_level.txt
practical_cryptography_for_developers-2024.3.4.0.dist-info/RECORD
